bodyjim/__init__.py
bodyjim/data_stream.py
bodyjim/env.py
bodyjim/schema.py
bodyjim/wrappers.py
bodyjim-1.0.3.dist-info/LICENSE
bodyjim-1.0.3.dist-info/METADATA
bodyjim-1.0.3.dist-info/WHEEL
bodyjim-1.0.3.dist-info/top_level.txt
bodyjim-1.0.3.dist-info/RECORD
