Metadata-Version: 2.1
Name: bodyjim
Version: 1.0.3
Summary: Comma body gymnasium API
Author-email: Vehicle Researcher <user@comma.ai>
License: MIT License
Project-URL: Homepage, https://github.com/commaai/body-jim
Project-URL: Bug Tracker, https://github.com/commaai/body-jim/issues
Classifier: Programming Language :: Python :: 3
Classifier: License :: OSI Approved :: MIT License
Classifier: Operating System :: OS Independent
Requires-Python: >=3.11
License-File: LICENSE
Requires-Dist: teleoprtc >=1.0.1
Requires-Dist: aiortc >=1.6.0
Requires-Dist: aiohttp >=3.7.0
Requires-Dist: gymnasium >=0.29.0
Requires-Dist: numpy >=1.19.0
Requires-Dist: pygame
Provides-Extra: dev
Requires-Dist: pre-commit ; extra == 'dev'
Provides-Extra: examples
Requires-Dist: opencv-python ; extra == 'examples'
Requires-Dist: onnx ; extra == 'examples'
Requires-Dist: onnxruntime ; extra == 'examples'
Requires-Dist: onnxruntime-gpu ; extra == 'examples'
